my_streamlit_component/__init__.py
my_streamlit_component/my_component.py
my_streamlit_component/st_chart_component.py
my_streamlit_component-0.1.1.dist-info/METADATA
my_streamlit_component-0.1.1.dist-info/WHEEL
my_streamlit_component-0.1.1.dist-info/top_level.txt
my_streamlit_component-0.1.1.dist-info/RECORD
