Metadata-Version: 2.1
Name: my-streamlit-component
Version: 0.1.1
Summary: A custom Streamlit component for Chart.js
Home-page: UNKNOWN
Author: Charly Wargnier
Author-email: cwar05@gnail.com
License: UNKNOWN
Platform: UNKNOWN
Classifier: Programming Language :: Python :: 3
Classifier: License :: OSI Approved :: MIT License
Classifier: Operating System :: OS Independent
Requires-Dist: streamlit
